userdetect.py
userdetect-0.1.0.dist-info/LICENSE
userdetect-0.1.0.dist-info/METADATA
userdetect-0.1.0.dist-info/WHEEL
userdetect-0.1.0.dist-info/RECORD
