Metadata-Version: 2.1
Name: userdetect
Version: 0.1.0
Summary: Ansible module to detect the existence of user(s) on UNIX operation systems. 
Home-page: https://github.com/Josef-Friedrich/ansible-module-userdetect
License: GPL-3.0-only
Author: Josef Friedrich
Author-email: josef@friedrich.rocks
Requires-Python: >=3.10,<4.0
Classifier: License :: OSI Approved :: GNU General Public License v3 (GPLv3)
Classifier: Programming Language :: Python :: 3
Classifier: Programming Language :: Python :: 3.10
Classifier: Programming Language :: Python :: 3.11
Classifier: Programming Language :: Python :: 3.12
Classifier: Programming Language :: Python :: 3 :: Only
Requires-Dist: ansible (>=9,<10)
Project-URL: Repository, https://github.com/Josef-Friedrich/ansible-module-userdetect
